<?xml version='1.0' encoding='UTF-8'?>

<!DOCTYPE hibernate-mapping PUBLIC

 "-//Hibernate/Hibernate Mapping DTD //EN"

 "http://hibernate.sourceforge.net/hibernate-mapping-3.0.dtd">



 <hibernate-mapping>

 <class name="com.hcl.Employee" table="emp1000">

  <id name="id" column="empid">

   <generator class="assigned"></generator>

  </id>



  <property name="name" column="empName"></property>

  <property name="salary"></property>

  <property name="dob"></property>



 </class>
 </hibernate-mapping>